{
  "version": 1,
  "serviceConfiguration": {
    "apiName": "quasarv2tiahold",
    "serviceName": "AppSync",
    "gqlSchemaPath": "/tmp/amplify-3423fe0d-70d1-429f-8675-2cea292e187b/amplify/backend/api/quasarv2tiahold/schema.graphql",
    "defaultAuthType": {
      "mode": "API_KEY",
      "keyDescription": "api key description",
      "expirationTime": 30
    },
    "additionalAuthTypes": [
      {
        "mode": "AWS_IAM"
      }
    ],
    "conflictResolution": {
      "defaultResolutionStrategy": {
        "type": "AUTOMERGE"
      }
    }
  }
}